runnynose
