Metadata-Version: 1.0
Name: runnynose
Version: 0.1.1
Summary: A continuous nose runner that tracks dependencies
Home-page: UNKNOWN
Author: Matthew J Desmarais
Author-email: matthew.desmarais@gmail.com
License: MIT
Platform: UNKNOWN
